cythKronPlus.cpython-38-darwin.so
cythLeastR.cpython-38-darwin.so
pySPaRTAN_helper/__init__.py
pySPaRTAN_helper-0.0.1.dist-info/METADATA
pySPaRTAN_helper-0.0.1.dist-info/WHEEL
pySPaRTAN_helper-0.0.1.dist-info/top_level.txt
pySPaRTAN_helper-0.0.1.dist-info/RECORD
