Metadata-Version: 2.1
Name: pySPaRTAN-helper
Version: 0.0.1
Requires-Dist: numpy (>=1.19.2)
